HROCH/__init__.py
HROCH/classifier.py
HROCH/fuzzy.py
HROCH/hroch.bin
HROCH/hroch.dll
HROCH/hroch.py
HROCH/regressor.py
HROCH/version.py
HROCH-1.4.12.dist-info/LICENSE
HROCH-1.4.12.dist-info/METADATA
HROCH-1.4.12.dist-info/WHEEL
HROCH-1.4.12.dist-info/top_level.txt
HROCH-1.4.12.dist-info/RECORD
