Metadata-Version: 2.1
Name: HROCH
Version: 1.4.12
Summary: Symbolic regression and classification
Home-page: https://github.com/janoPig/HROCH/
Author: Jano
Author-email: hroch.regression@gmail.com
License: MIT
Project-URL: Documentation, https://janopig.github.io/HROCH/HROCH.html
Project-URL: Source, https://github.com/janoPig/HROCH
Project-URL: Tracker, https://github.com/janoPig/HROCH/issues
Keywords: scikit-learn,symbolic-regression,classification,fuzzy-logic,interpretable-ml,machine-learning
Classifier: Operating System :: Microsoft :: Windows
Classifier: Operating System :: POSIX :: Linux
Classifier: Topic :: Scientific/Engineering :: Artificial Intelligence
Classifier: License :: OSI Approved :: MIT License
Classifier: Programming Language :: Python
Classifier: Programming Language :: Python :: 3
Classifier: Programming Language :: Python :: 3.8
Classifier: Programming Language :: Python :: 3.9
Classifier: Programming Language :: Python :: 3.10
Classifier: Programming Language :: Python :: 3.11
Classifier: Programming Language :: Python :: 3.12
License-File: LICENSE
Requires-Dist: numpy
Requires-Dist: scikit-learn
Requires-Dist: scipy
